<?xml version="1.0" encoding="UTF-8"?>
<list xmlns:xsi="http://www.w3.org/2001/XMLSchema-instance" xsi:noNamespaceSchemaLocation="items.xsd">
    <item id="43104" type="Armor" name="Ferrum Helmet">
        <set name="icon" val="Asuki_Icon.armor_helmet_i00" />
        <set name="default_action" val="EQUIP" />
        <set name="bodypart" val="head" />
        <set name="immediate_effect" val="1" />
        <set name="crystal_count" val="1005" />
        <set name="crystal_type" val="S84" />
        <set name="material" val="BONE" />
        <set name="weight" val="530" />
        <set name="price" val="20940000" />
        <set name="element_enabled" val="true" />
        <set name="enchant_enabled" val="1" />
        <cond msgId="1518">
            <player races="HUMAN,ELF,DARK_ELF,ORC,DWARF" />
        </cond>
        <for>
            <add stat="pDef" val="110" />
            <enchant stat="pDef" val="0" />
        </for>
    </item>
    <item id="43109" type="Armor" name="Ferrum Leather Helmet">
        <set name="icon" val="Asuki_Icon.armor_leather_helmet_i00" />
        <set name="default_action" val="EQUIP" />
        <set name="bodypart" val="head" />
        <set name="immediate_effect" val="1" />
        <set name="crystal_count" val="1005" />
        <set name="crystal_type" val="S84" />
        <set name="material" val="BONE" />
        <set name="weight" val="530" />
        <set name="price" val="20940000" />
        <set name="element_enabled" val="true" />
        <set name="enchant_enabled" val="1" />
        <for>
            <add stat="pDef" val="110" />
            <enchant stat="pDef" val="0" />
        </for>
    </item>
    <item id="43114" type="Armor" name="Ferrum Circlet">
        <set name="icon" val="Asuki_Icon.armor_circlet_i00" />
        <set name="default_action" val="EQUIP" />
        <set name="bodypart" val="head" />
        <set name="immediate_effect" val="1" />
        <set name="crystal_count" val="1005" />
        <set name="crystal_type" val="S84" />
        <set name="material" val="BONE" />
        <set name="weight" val="530" />
        <set name="price" val="20940000" />
        <set name="element_enabled" val="true" />
        <set name="enchant_enabled" val="1" />
        <cond msgId="1518">
            <player races="HUMAN,ELF,DARK_ELF,ORC,DWARF" />
        </cond>
        <for>
            <add stat="pDef" val="110" />
            <enchant stat="pDef" val="0" />
        </for>
    </item>
    <item id="43100" type="Armor" name="Ferrum Breastplate">
        <set name="icon" val="Asuki_Icon.armor_t701_u_i00" />
        <set name="default_action" val="EQUIP" />
        <set name="armor_type" val="HEAVY" />
        <set name="bodypart" val="chest" />
        <set name="immediate_effect" val="1" />
        <set name="crystal_count" val="2680" />
        <set name="crystal_type" val="S84" />
        <set name="material" val="BRONZE" />
        <set name="weight" val="7520" />
        <set name="price" val="55840000" />
        <set name="element_enabled" val="true" />
        <set name="enchant_enabled" val="1" />
        <cond msgId="1518">
            <player races="HUMAN,ELF,DARK_ELF,ORC,DWARF" />
        </cond>
        <for>
            <add stat="pDef" val="272" />
            <enchant stat="pDef" val="0" />
        </for>
    </item>
    <item id="43105" type="Armor" name="Ferrum Leather Breastplate">
        <set name="icon" val="Asuki_Icon.armor_t702_u_i00" />
        <set name="default_action" val="EQUIP" />
        <set name="armor_type" val="LIGHT" />
        <set name="bodypart" val="chest" />
        <set name="immediate_effect" val="1" />
        <set name="crystal_count" val="2010" />
        <set name="crystal_type" val="S84" />
        <set name="material" val="BRONZE" />
        <set name="weight" val="4140" />
        <set name="price" val="41880000" />
        <set name="element_enabled" val="true" />
        <set name="enchant_enabled" val="1" />
        <for>
            <add stat="pDef" val="204" />
            <enchant stat="pDef" val="0" />
        </for>
    </item>
    <item id="43110" type="Armor" name="Ferrum Tunic">
        <set name="icon" val="Asuki_Icon.armor_t703_u_i00" />
        <set name="default_action" val="EQUIP" />
        <set name="armor_type" val="MAGIC" />
        <set name="bodypart" val="chest" />
        <set name="immediate_effect" val="1" />
        <set name="crystal_count" val="2010" />
        <set name="crystal_type" val="S84" />
        <set name="material" val="BRONZE" />
        <set name="weight" val="1750" />
        <set name="price" val="41880000" />
        <set name="element_enabled" val="true" />
        <set name="enchant_enabled" val="1" />
        <cond msgId="1518">
            <player races="HUMAN,ELF,DARK_ELF,ORC,DWARF" />
        </cond>
        <for>
            <add stat="pDef" val="136" />
            <add stat="maxMp" val="661" />
            <enchant stat="pDef" val="0" />
        </for>
    </item>
    <item id="43101" type="Armor" name="Ferrum Gaiter">
        <set name="icon" val="Asuki_Icon.armor_t701_l_i00" />
        <set name="default_action" val="EQUIP" />
        <set name="armor_type" val="HEAVY" />
        <set name="bodypart" val="legs" />
        <set name="immediate_effect" val="1" />
        <set name="crystal_count" val="1675" />
        <set name="crystal_type" val="S84" />
        <set name="material" val="SCALE_OF_DRAGON" />
        <set name="weight" val="3170" />
        <set name="price" val="34900000" />
        <set name="element_enabled" val="true" />
        <set name="enchant_enabled" val="1" />
        <cond msgId="1518">
            <player races="HUMAN,ELF,DARK_ELF,ORC,DWARF" />
        </cond>
        <for>
            <add stat="pDef" val="170" />
            <enchant stat="pDef" val="0" />
        </for>
    </item>
    <item id="43106" type="Armor" name="Ferrum leather Legging">
        <set name="icon" val="Asuki_Icon.armor_t702_l_i00" />
        <set name="default_action" val="EQUIP" />
        <set name="armor_type" val="LIGHT" />
        <set name="bodypart" val="legs" />
        <set name="immediate_effect" val="1" />
        <set name="crystal_count" val="1256" />
        <set name="crystal_type" val="S84" />
        <set name="material" val="SCALE_OF_DRAGON" />
        <set name="weight" val="1320" />
        <set name="price" val="26175000" />
        <set name="element_enabled" val="true" />
        <set name="enchant_enabled" val="1" />
        <for>
            <add stat="pDef" val="128" />
            <enchant stat="pDef" val="0" />
        </for>
    </item>
    <item id="43111" type="Armor" name="Ferrum Stockings">
        <set name="icon" val="Asuki_Icon.armor_t703_l_i00" />
        <set name="default_action" val="EQUIP" />
        <set name="armor_type" val="MAGIC" />
        <set name="bodypart" val="legs" />
        <set name="immediate_effect" val="1" />
        <set name="crystal_count" val="1256" />
        <set name="crystal_type" val="S84" />
        <set name="material" val="SCALE_OF_DRAGON" />
        <set name="weight" val="850" />
        <set name="price" val="26175000" />
        <set name="element_enabled" val="true" />
        <set name="enchant_enabled" val="1" />
        <cond msgId="1518">
            <player races="HUMAN,ELF,DARK_ELF,ORC,DWARF" />
        </cond>
        <for>
            <add stat="pDef" val="85" />
            <add stat="maxMp" val="439" />
            <enchant stat="pDef" val="0" />
        </for>
    </item>
    <item id="43102" type="Armor" name="Ferrum Gauntlet">
        <set name="icon" val="Asuki_Icon.armor_t701_g_i00" />
        <set name="default_action" val="EQUIP" />
        <set name="bodypart" val="gloves" />
        <set name="immediate_effect" val="1" />
        <set name="crystal_count" val="670" />
        <set name="crystal_type" val="S84" />
        <set name="material" val="LEATHER" />
        <set name="weight" val="510" />
        <set name="price" val="13960000" />
        <set name="element_enabled" val="true" />
        <set name="enchant_enabled" val="1" />
        <cond msgId="1518">
            <player races="HUMAN,ELF,DARK_ELF,ORC,DWARF" />
        </cond>
        <for>
            <add stat="pDef" val="74" />
            <enchant stat="pDef" val="0" />
        </for>
    </item>
    <item id="43107" type="Armor" name="Ferrum Leather Gloves">
        <set name="icon" val="Asuki_Icon.armor_t702_g_i00" />
        <set name="default_action" val="EQUIP" />
        <set name="bodypart" val="gloves" />
        <set name="immediate_effect" val="1" />
        <set name="crystal_count" val="670" />
        <set name="crystal_type" val="S84" />
        <set name="material" val="LEATHER" />
        <set name="weight" val="510" />
        <set name="price" val="13960000" />
        <set name="element_enabled" val="true" />
        <set name="enchant_enabled" val="1" />
        <for>
            <add stat="pDef" val="74" />
            <enchant stat="pDef" val="0" />
        </for>
    </item>
    <item id="43112" type="Armor" name="Ferrum Gloves">
        <set name="icon" val="Asuki_Icon.armor_t703_g_i00" />
        <set name="default_action" val="EQUIP" />
        <set name="bodypart" val="gloves" />
        <set name="immediate_effect" val="1" />
        <set name="crystal_count" val="670" />
        <set name="crystal_type" val="S84" />
        <set name="material" val="LEATHER" />
        <set name="weight" val="510" />
        <set name="price" val="13960000" />
        <set name="element_enabled" val="true" />
        <set name="enchant_enabled" val="1" />
        <cond msgId="1518">
            <player races="HUMAN,ELF,DARK_ELF,ORC,DWARF" />
        </cond>
        <for>
            <add stat="pDef" val="74" />
            <enchant stat="pDef" val="0" />
        </for>
    </item>
    <item id="43103" type="Armor" name="Ferrum Boots">
        <set name="icon" val="Asuki_Icon.armor_t701_b_i00" />
        <set name="default_action" val="EQUIP" />
        <set name="bodypart" val="feet" />
        <set name="immediate_effect" val="1" />
        <set name="crystal_count" val="670" />
        <set name="crystal_type" val="S84" />
        <set name="material" val="LEATHER" />
        <set name="weight" val="1070" />
        <set name="price" val="13960000" />
        <set name="element_enabled" val="true" />
        <set name="enchant_enabled" val="1" />
        <cond msgId="1518">
            <player races="HUMAN,ELF,DARK_ELF,ORC,DWARF" />
        </cond>
        <for>
            <add stat="pDef" val="74" />
            <enchant stat="pDef" val="0" />
        </for>
    </item>
    <item id="43108" type="Armor" name="Ferrum Leather Boots">
        <set name="icon" val="Asuki_Icon.armor_t702_b_i00" />
        <set name="default_action" val="EQUIP" />
        <set name="bodypart" val="feet" />
        <set name="immediate_effect" val="1" />
        <set name="crystal_count" val="670" />
        <set name="crystal_type" val="S84" />
        <set name="material" val="LEATHER" />
        <set name="weight" val="1070" />
        <set name="price" val="13960000" />
        <set name="element_enabled" val="true" />
        <set name="enchant_enabled" val="1" />
        <for>
            <add stat="pDef" val="74" />
            <enchant stat="pDef" val="0" />
        </for>
    </item>
    <item id="43113" type="Armor" name="Ferrum Shoes">
        <set name="icon" val="Asuki_Icon.armor_t703_b_i00" />
        <set name="default_action" val="EQUIP" />
        <set name="bodypart" val="feet" />
        <set name="immediate_effect" val="1" />
        <set name="crystal_count" val="670" />
        <set name="crystal_type" val="S84" />
        <set name="material" val="LEATHER" />
        <set name="weight" val="1070" />
        <set name="price" val="13960000" />
        <set name="element_enabled" val="true" />
        <set name="enchant_enabled" val="1" />
        <cond msgId="1518">
            <player races="HUMAN,ELF,DARK_ELF,ORC,DWARF" />
        </cond>
        <for>
            <add stat="pDef" val="74" />
            <enchant stat="pDef" val="0" />
        </for>
    </item>
    <item id="43115" type="Armor" name="Ferrum Breastplate {PvP}">
        <set name="icon" val="Asuki_Icon.armor_t701_u_i00" />
        <set name="default_action" val="EQUIP" />
        <set name="armor_type" val="HEAVY" />
        <set name="bodypart" val="chest" />
        <set name="immediate_effect" val="1" />
        <set name="crystal_count" val="2680" />
        <set name="crystal_type" val="S84" />
        <set name="material" val="BRONZE" />
        <set name="weight" val="7520" />
        <set name="price" val="55840000" />
        <set name="is_tradable" val="false" />
        <set name="is_dropable" val="false" />
        <set name="is_sellable" val="false" />
        <set name="enchant_enabled" val="1" />
        <cond msgId="1518">
            <player races="HUMAN,ELF,DARK_ELF,ORC,DWARF" />
        </cond>
        <for>
            <add stat="pDef" val="272" />
            <enchant stat="pDef" val="0" />
        </for>
    </item>
    <item id="43116" type="Armor" name="Ferrum Leather Breastplate {PvP}">
        <set name="icon" val="Asuki_Icon.armor_t702_u_i00" />
        <set name="default_action" val="EQUIP" />
        <set name="armor_type" val="LIGHT" />
        <set name="bodypart" val="chest" />
        <set name="immediate_effect" val="1" />
        <set name="crystal_count" val="2010" />
        <set name="crystal_type" val="S84" />
        <set name="material" val="BRONZE" />
        <set name="weight" val="4140" />
        <set name="price" val="41880000" />
        <set name="is_tradable" val="false" />
        <set name="is_dropable" val="false" />
        <set name="is_sellable" val="false" />
        <set name="enchant_enabled" val="1" />
        <for>
            <add stat="pDef" val="204" />
            <enchant stat="pDef" val="0" />
        </for>
    </item>
    <item id="43117" type="Armor" name="Ferrum Tunic {PvP}">
        <set name="icon" val="Asuki_Icon.armor_t703_u_i00" />
        <set name="default_action" val="EQUIP" />
        <set name="armor_type" val="MAGIC" />
        <set name="bodypart" val="chest" />
        <set name="immediate_effect" val="1" />
        <set name="crystal_count" val="2010" />
        <set name="crystal_type" val="S84" />
        <set name="material" val="BRONZE" />
        <set name="weight" val="1750" />
        <set name="price" val="41880000" />
        <set name="enchant_enabled" val="1" />
        <set name="is_tradable" val="false" />
        <set name="is_dropable" val="false" />
        <set name="is_sellable" val="false" />
        <cond msgId="1518">
            <player races="HUMAN,ELF,DARK_ELF,ORC,DWARF" />
        </cond>
        <for>
            <add stat="pDef" val="136" />
            <add stat="maxMp" val="661" />
            <enchant stat="pDef" val="0" />
        </for>
    </item>
</list>
